scheduled_thread_pool_executor/ScheduledTask.py
scheduled_thread_pool_executor/ScheduledThreadPoolExecutor.py
scheduled_thread_pool_executor/__init__.py
scheduled_thread_pool_executor-1.0.2.dist-info/LICENSE.txt
scheduled_thread_pool_executor-1.0.2.dist-info/METADATA
scheduled_thread_pool_executor-1.0.2.dist-info/WHEEL
scheduled_thread_pool_executor-1.0.2.dist-info/top_level.txt
scheduled_thread_pool_executor-1.0.2.dist-info/RECORD
