Metadata-Version: 2.1
Name: scheduled-thread-pool-executor
Version: 1.0.2
Summary: Add a short description here!
Home-page: https://github.com/syogaraj/scheduled_thread_pool_executor
Author: Yogaraj.S
Author-email: yoga30696@gmail.com
License: MIT
Project-URL: Documentation, https://pyscaffold.org/
Platform: any
Classifier: Development Status :: 5 - Production/Stable
Classifier: Programming Language :: Python
Classifier: Topic :: Utilities
Classifier: License :: OSI Approved :: MIT License
License-File: LICENSE.txt
Requires-Dist: delayedqueue (>="1.0.0")
Requires-Dist: importlib-metadata ; python_version < "3.8"
Provides-Extra: testing
Requires-Dist: setuptools ; extra == 'testing'
Requires-Dist: pytest ; extra == 'testing'
Requires-Dist: pytest-cov ; extra == 'testing'
